autopentest/__init__.py
autopentest/ai_analyzer.cpython-313-x86_64-linux-gnu.so
autopentest/autopentest.py
autopentest/autopentest_core.cpython-313-x86_64-linux-gnu.so
autopentest/config.py
autopentest/main.py
autopentest/utils.py
tautopentest-2.1.3.dist-info/METADATA
tautopentest-2.1.3.dist-info/WHEEL
tautopentest-2.1.3.dist-info/entry_points.txt
tautopentest-2.1.3.dist-info/top_level.txt
tautopentest-2.1.3.dist-info/RECORD
tautopentest-2.1.3.dist-info/licenses/LICENSE
