Metadata-Version: 2.4
Name: TAutoPentest
Version: 2.1.3
Summary: AI-Powered Automated Penetration Testing Tool
Home-page: https://github.com/mostaghell/TAutoPentest
Author: D3F417
Author-email: info@tcommunity.pro
License: Proprietary
Project-URL: Bug Reports, https://github.com/mostaghell/TAutoPentest/issues
Project-URL: Source, https://github.com/mostaghell/TAutoPentest
Project-URL: Documentation, https://github.com/mostaghell/TAutoPentest/wiki
Keywords: penetration-testing security ai automation cybersecurity vulnerability-scanner
Classifier: Development Status :: 4 - Beta
Classifier: Intended Audience :: Information Technology
Classifier: Topic :: Security
Classifier: Topic :: System :: Networking :: Monitoring
Classifier: License :: Other/Proprietary License
Classifier: Programming Language :: Python :: 3
Classifier: Programming Language :: Python :: 3.7
Classifier: Programming Language :: Python :: 3.8
Classifier: Programming Language :: Python :: 3.9
Classifier: Programming Language :: Python :: 3.10
Classifier: Programming Language :: Python :: 3.11
Classifier: Programming Language :: Python :: 3.12
Classifier: Operating System :: OS Independent
Classifier: Environment :: Console
Requires-Python: >=3.7
License-File: LICENSE
Requires-Dist: colorama>=0.4.4
Requires-Dist: requests>=2.25.1
Dynamic: author
Dynamic: author-email
Dynamic: classifier
Dynamic: description
Dynamic: description-content-type
Dynamic: home-page
Dynamic: keywords
Dynamic: license
Dynamic: license-file
Dynamic: project-url
Dynamic: requires-dist
Dynamic: requires-python
Dynamic: summary
